deepadvancer/__init__.py
deepadvancer/deepadvancer.py
deepadvancer/process_batch_correction.R
deepadvancer/shared_logFC_analysis.R
deepadvancer-0.1.0.dist-info/licenses/LICENSE.txt
deepadvancer-0.1.0.dist-info/METADATA
deepadvancer-0.1.0.dist-info/WHEEL
deepadvancer-0.1.0.dist-info/top_level.txt
deepadvancer-0.1.0.dist-info/RECORD
