Metadata-Version: 2.4
Name: deepadvancer
Version: 0.1.0
Summary: A batch correction and signal deconvolution toolkit for bulk transcriptomic data using adversarial autoencoder
Home-page: https://github.com/BioinAI/deepadvancer
Author: Mintian Cui
Author-email: 1308318910@qq.com
License: MIT
Keywords: bulk RNA-seq batch-correction autoencoder deconvolution bioinformatics adversarial deep learning
Classifier: Development Status :: 4 - Beta
Classifier: Programming Language :: Python :: 3
Classifier: License :: OSI Approved :: MIT License
Classifier: Operating System :: OS Independent
Classifier: Intended Audience :: Science/Research
Classifier: Topic :: Scientific/Engineering :: Bio-Informatics
Classifier: Topic :: Scientific/Engineering :: Artificial Intelligence
Requires-Python: >=3.9
License-File: LICENSE.txt
Requires-Dist: torch<2.4,>=2.0
Requires-Dist: numpy<1.27,>=1.26
Requires-Dist: pandas<2.3,>=2.2
Requires-Dist: tqdm<4.67,>=4.66
Requires-Dist: matplotlib<3.7,>=3.6
Requires-Dist: scikit-learn<1.5,>=1.4
Requires-Dist: scipy<1.13,>=1.12
Requires-Dist: rpy2<3.7,>=3.6
Dynamic: author
Dynamic: author-email
Dynamic: classifier
Dynamic: description
Dynamic: description-content-type
Dynamic: home-page
Dynamic: keywords
Dynamic: license
Dynamic: license-file
Dynamic: requires-dist
Dynamic: requires-python
Dynamic: summary
